upy2/__init__.py
upy2/core.py
upy2/dependency.py
upy2/id_generator.py
upy2/sessions.py
upy2/typesetting/__init__.py
upy2/typesetting/engineering.py
upy2/typesetting/engineering_rel.py
upy2/typesetting/fixedpoint.py
upy2/typesetting/fixedpoint_rel.py
upy2/typesetting/fixedpoint_relu.py
upy2/typesetting/numbers.py
upy2/typesetting/protocol.py
upy2/typesetting/rules.py
upy2/typesetting/scientific.py
upy2/typesetting/scientific_rel.py
upy2/typesetting/scientific_relu.py
upy2-2.3.4.dist-info/LICENSE
upy2-2.3.4.dist-info/METADATA
upy2-2.3.4.dist-info/WHEEL
upy2-2.3.4.dist-info/top_level.txt
upy2-2.3.4.dist-info/RECORD
