Metadata-Version: 2.1
Name: upy2
Version: 2.3.4
Summary: Uncertainty propagation of intercorrelated multidimensional quantities
Author-email: Friedrich Romstedt <friedrichromstedt@gmail.com>
Project-URL: Repository, https://github.com/friedrichromstedt/upy/
Classifier: Development Status :: 5 - Production/Stable
Classifier: Environment :: Console
Classifier: Intended Audience :: End Users/Desktop
Classifier: Intended Audience :: Science/Research
Classifier: License :: OSI Approved :: MIT License
Classifier: Operating System :: OS Independent
Classifier: Programming Language :: Python :: 3
Classifier: Topic :: Scientific/Engineering
License-File: LICENSE
Requires-Dist: numpy
